[
        {
            "object": "media_type",
            "id": "image",
            "code": "image",
            "name": "Stock Image ・ Animated GIF",
            "name_plural": "Stock Image ・ Animated GIF",
            "name_seo": "Stock Image ・ Animated GIF",
            "name_seo_plural": "Stock Image ・ Animated GIF",
            "name_short": "Image",
            "name_short_plural": "Image",
            "video": false,
            "audio": false,
            "group": "image",
            "sub_media_types": [
                "photo",
                "vector",
                "gif"
            ]
        },
        {
            "object": "media_type",
            "id": "video",
            "code": "video",
            "name": "Stock video footage",
            "name_plural": "Stock video footage",
            "name_seo": "Stock video footage",
            "name_seo_plural": "Stock video footage",
            "name_short": "Video",
            "name_short_plural": "Video",
            "video": false,
            "audio": false,
            "group": "video",
            "sub_media_types": [
                "animation",
                "video_live",
                "video_vr"
            ]
        },
        {
            "object": "media_type",
            "id": "ae",
            "code": "ae",
            "name": "After Effects",
            "name_plural": "After Effects",
            "name_seo": "After Effects",
            "name_seo_plural": "After Effects",
            "name_short": "AE",
            "name_short_plural": "AE",
            "video": false,
            "audio": false,
            "group": "ae",
            "sub_media_types": [
                "ae_template",
                "ae_preset"
            ]
        },
        {
            "object": "media_type",
            "id": "pr",
            "code": "pr",
            "name": "Premiere Pro",
            "name_plural": "Premiere Pro",
            "name_seo": "Premiere Pro",
            "name_seo_plural": "Premiere Pro",
            "name_short": "Premiere",
            "name_short_plural": "Premiere",
            "video": false,
            "audio": false,
            "group": "pr",
            "sub_media_types": [
                "pr_template",
                "mg_template",
                "pr_preset"
            ]
        },
        {
            "object": "media_type",
            "id": "fcp",
            "code": "fcp",
            "name": "Apple Motion / FCPX Templates",
            "name_plural": "Apple Motion / FCPX Templates",
            "name_seo": "Apple Motion / FCPX Templates",
            "name_seo_plural": "Apple Motion / FCPX Templates",
            "name_short": "FCPX ・ Motion",
            "name_short_plural": "FCPX ・ Motion",
            "video": false,
            "audio": false,
            "group": "fcp",
            "sub_media_types": [
                "motion_template"
            ]
        },
        {
            "object": "media_type",
            "id": "resolve",
            "code": "resolve",
            "name": "DaVinci Resolve",
            "name_plural": "DaVinci Resolve",
            "name_seo": "DaVinci Resolve",
            "name_seo_plural": "DaVinci Resolve",
            "name_short": "DaVinci Resolve",
            "name_short_plural": "DaVinci Resolve",
            "video": false,
            "audio": false,
            "group": "resolve",
            "sub_media_types": [
                "resolve_template",
                "resolve_macro"
            ]
        },
        {
            "object": "media_type",
            "id": "3d",
            "code": "3d",
            "name": "3D models",
            "name_plural": "3D models",
            "name_seo": "3D models",
            "name_seo_plural": "3D models",
            "name_short": "3D",
            "name_short_plural": "3D",
            "video": false,
            "audio": false,
            "group": "3d",
            "sub_media_types": [
                "3d_model"
            ]
        },
        {
            "object": "media_type",
            "id": "1",
            "code": "photo",
            "name": "Stock Photo",
            "name_plural": "Stock Photo",
            "name_seo": "Stock Photo",
            "name_seo_plural": "Stock Photo",
            "name_short": "Photo",
            "name_short_plural": "Photo",
            "video": false,
            "audio": false,
            "group": "image",
            "sub_media_types": []
        },
        {
            "object": "media_type",
            "id": "2",
            "code": "vector",
            "name": "Stock Vector",
            "name_plural": "Stock Vector",
            "name_seo": "Stock Vector",
            "name_seo_plural": "Stock Vector",
            "name_short": "Vector",
            "name_short_plural": "Vector",
            "video": false,
            "audio": false,
            "group": "image",
            "sub_media_types": []
        },
        {
            "object": "media_type",
            "id": "3",
            "code": "animation",
            "name": "Stock Animation",
            "name_plural": "Stock Animation",
            "name_seo": "Stock Animation",
            "name_seo_plural": "Stock Animation",
            "name_short": "Animation",
            "name_short_plural": "Animation",
            "video": true,
            "audio": false,
            "group": "video",
            "sub_media_types": []
        },
        {
            "object": "media_type",
            "id": "4",
            "code": "video_live",
            "name": "Live Action",
            "name_plural": "Live Action",
            "name_seo": "Live Action",
            "name_seo_plural": "Live Action",
            "name_short": "Live Action",
            "name_short_plural": "Live Action",
            "video": false,
            "audio": false,
            "group": "video",
            "sub_media_types": []
        },
        {
            "object": "media_type",
            "id": "5",
            "code": "3d_model",
            "name": "3D models",
            "name_plural": "3D models",
            "name_seo": "3D models",
            "name_seo_plural": "3D models",
            "name_short": "3D",
            "name_short_plural": "3D",
            "video": false,
            "audio": false,
            "group": "3d",
            "sub_media_types": []
        },
        {
            "object": "media_type",
            "id": "6",
            "code": "music",
            "name": "Background music for video",
            "name_plural": "Background music for video",
            "name_seo": "Background music for video",
            "name_seo_plural": "Background music for video",
            "name_short": "Music",
            "name_short_plural": "Music",
            "video": false,
            "audio": true,
            "group": "music",
            "sub_media_types": []
        },
        {
            "object": "media_type",
            "id": "7",
            "code": "sfx",
            "name": "Sound Effects for Video",
            "name_plural": "Sound Effects for Video",
            "name_seo": "Sound Effects for Video",
            "name_seo_plural": "Sound Effects for Video",
            "name_short": "SFX",
            "name_short_plural": "SFX",
            "video": false,
            "audio": true,
            "group": "sfx",
            "sub_media_types": []
        },
        {
            "object": "media_type",
            "id": "8",
            "code": "ae_template",
            "name": "After Effects templates",
            "name_plural": "After Effects templates",
            "name_seo": "After Effects templates",
            "name_seo_plural": "After Effects templates",
            "name_short": "AE",
            "name_short_plural": "AE",
            "video": false,
            "audio": false,
            "group": "ae",
            "sub_media_types": []
        },
        {
            "object": "media_type",
            "id": "9",
            "code": "motion_template",
            "name": "Apple Motion templates",
            "name_plural": "Apple Motion templates",
            "name_seo": "Apple Motion templates",
            "name_seo_plural": "Apple Motion templates",
            "name_short": "Apple Motion",
            "name_short_plural": "Apple Motion",
            "video": false,
            "audio": false,
            "group": "fcp",
            "sub_media_types": []
        },
        {
            "object": "media_type",
            "id": "11",
            "code": "photo_vr",
            "name": "360° Photo",
            "name_plural": "360° Photo",
            "name_seo": "360° Photo",
            "name_seo_plural": "360° Photo",
            "name_short": "360° Photo",
            "name_short_plural": "360° Photo",
            "video": false,
            "audio": false,
            "group": "image",
            "sub_media_types": []
        },
        {
            "object": "media_type",
            "id": "12",
            "code": "video_vr",
            "name": "360° Video",
            "name_plural": "360° Video",
            "name_seo": "360° Video",
            "name_seo_plural": "360° Video",
            "name_short": "360° Video",
            "name_short_plural": "360° Video",
            "video": false,
            "audio": false,
            "group": "video",
            "sub_media_types": []
        },
        {
            "object": "media_type",
            "id": "14",
            "code": "gif",
            "name": "GIF",
            "name_plural": "GIF",
            "name_seo": "GIF",
            "name_seo_plural": "GIF",
            "name_short": "GIF",
            "name_short_plural": "GIF",
            "video": true,
            "audio": false,
            "group": "image",
            "sub_media_types": []
        },
        {
            "object": "media_type",
            "id": "15",
            "code": "pr_template",
            "name": "Premiere Pro Template",
            "name_plural": "Premiere Pro Template",
            "name_seo": "Premiere Pro Template",
            "name_seo_plural": "Premiere Pro Template",
            "name_short": "Premiere",
            "name_short_plural": "Premiere",
            "video": false,
            "audio": false,
            "group": "pr",
            "sub_media_types": []
        },
        {
            "object": "media_type",
            "id": "16",
            "code": "mg_template",
            "name": "Motion Graphics Template",
            "name_plural": "Motion Graphics Template",
            "name_seo": "Motion Graphics Template",
            "name_seo_plural": "Motion Graphics Template",
            "name_short": "Motion Graphics",
            "name_short_plural": "Motion Graphics",
            "video": false,
            "audio": false,
            "group": "pr",
            "sub_media_types": []
        },
        {
            "object": "media_type",
            "id": "19",
            "code": "ae_preset",
            "name": "After Effects Animation Preset",
            "name_plural": "After Effects Animation Preset",
            "name_seo": "After Effects Animation Preset",
            "name_seo_plural": "After Effects Animation Preset",
            "name_short": "AE Preset",
            "name_short_plural": "AE Preset",
            "video": false,
            "audio": false,
            "group": "ae",
            "sub_media_types": []
        },
        {
            "object": "media_type",
            "id": "20",
            "code": "pr_preset",
            "name": "Premiere Pro Effect Preset",
            "name_plural": "Premiere Pro Effect Preset",
            "name_seo": "Premiere Pro Effect Preset",
            "name_seo_plural": "Premiere Pro Effect Preset",
            "name_short": "Premiere Preset",
            "name_short_plural": "Premiere Preset",
            "video": false,
            "audio": false,
            "group": "pr",
            "sub_media_types": []
        },
        {
            "object": "media_type",
            "id": "21",
            "code": "lottie",
            "name": "Lottie Animation",
            "name_plural": "Lottie Animation",
            "name_seo": "Lottie Animation",
            "name_seo_plural": "Lottie Animation",
            "name_short": "Lottie",
            "name_short_plural": "Lottie",
            "video": true,
            "audio": false,
            "group": "lottie",
            "sub_media_types": []
        },
        {
            "object": "media_type",
            "id": "22",
            "code": "resolve_template",
            "name": "DaVinci Resolve Template",
            "name_plural": "DaVinci Resolve Template",
            "name_seo": "DaVinci Resolve Template",
            "name_seo_plural": "DaVinci Resolve Template",
            "name_short": "DaVinci Resolve Template",
            "name_short_plural": "DaVinci Resolve Templates",
            "video": false,
            "audio": false,
            "group": "resolve",
            "sub_media_types": []
        },
        {
            "object": "media_type",
            "id": "23",
            "code": "resolve_macro",
            "name": "DaVinci Resolve Macro",
            "name_plural": "DaVinci Resolve Macro",
            "name_seo": "DaVinci Resolve Macro",
            "name_seo_plural": "DaVinci Resolve Macro",
            "name_short": "DaVinci Resolve Macro",
            "name_short_plural": "DaVinci Resolve Macro",
            "video": false,
            "audio": false,
            "group": "resolve",
            "sub_media_types": []
        },
        {
            "id": "gif_free",
            "code": "gif_free",
            "name": "Free Animated GIFs",
            "name_plural": "Free Animated GIFs",
            "name_short": "Free Stock GIFs",
            "name_short_plural": "Free Stock GIFs",
            "name_seo": "Free Animated GIFs",
            "name_seo_plural": "Free Animated GIFs"
          },
          {
            "id": "video_free",
            "code": "video_free",
            "name": "Free Stock Footage",
            "name_plural": "Free Stock Footage",
            "name_short": "Free Stock Video",
            "name_short_plural": "Free Stock Video",
            "name_seo": "Free Stock Footage",
            "name_seo_plural": "Free Stock Footage"
          },
          {
            "id": "ae_free",
            "code": "ae_free",
            "name": "Free After Effects Templates",
            "name_plural": "Free After Effects Templates",
            "name_short": "Free AE Templates",
            "name_short_plural": "Free AE Templates",
            "name_seo": "Free After Effects Templates",
            "name_seo_plural": "Free After Effects Templates"
          },
          {
            "id": "pr_free",
            "code": "pr_free",
            "name": "Free Premiere Pro Templates",
            "name_plural": "Free Premiere Pro Templates",
            "name_short": "Free Motion Graphics Template",
            "name_short_plural": "Free Motion Graphics Template",
            "name_seo": "Free Premiere Pro Templates",
            "name_seo_plural": "Free Premiere Pro Templates"
          },
          {
            "id": "fcp_free",
            "code": "fcp_free",
            "name": "Free FCPX Motion Templates",
            "name_plural": "Free FCPX Motion Templates",
            "name_short": "Free Final Cut Pro Templates",
            "name_short_plural": "Free Final Cut Pro Templates",
            "name_seo": "Free FCPX Motion Templates",
            "name_seo_plural": "Free FCPX Motion Templates"
          },
          {
            "id": "music_free",
            "code": "music_free",
            "name": "Free Background Music for Video",
            "name_plural": "Free Background Music for Video",
            "name_short": "Royalty Free Stock Music",
            "name_short_plural": "Royalty Free Stock Music",
            "name_seo": "Free Background Music for Video",
            "name_seo_plural": "Free Background Music for Video"
          },
          {
            "id": "sfx_free",
            "code": "sfx_free",
            "name": "Free Sound Effects",
            "name_plural": "Free Sound Effects",
            "name_short": "Free SFX",
            "name_short_plural": "Free SFX",
            "name_seo": "Free Sound Effects",
            "name_seo_plural": "Free Sound Effects"
          }
    ]
